{
    "date": "May 16, 2023",
    "Tiers": [
        {
            "tier": "Tier 1",
            "name": "Good Cards Stature"
        },
        {
            "tier": "Tier 1",
            "name": "Sera Control"
        },
        {
            "tier": "Tier 2",
            "name": "Sera Surfer"
        },
        {
            "tier": "Tier 2",
            "name": "DeathWave"
        },
        {
            "tier": "Tier 2",
            "name": "DoomWave"
        },
        {
            "tier": "Tier 2",
            "name": "Discard Dracula"
        },
        {
            "tier": "Tier 2",
            "name": "Devil Darkhawk"
        },
        {
            "tier": "Tier 2",
            "name": "Lockjaw Thor"
        },
        {
            "tier": "Tier 2",
            "name": "Nebula Control"
        },
        {
            "tier": "Tier 2",
            "name": "Galactus"
        },
        {
            "tier": "Tier 2",
            "name": "Patriot"
        },
        {
            "tier": "Tier 2",
            "name": "Thanos Control"
        },
        {
            "tier": "Tier 3",
            "name": "Shuri Sauron"
        },
        {
            "tier": "Tier 3",
            "name": "Hela Discard"
        },
        {
            "tier": "Tier 3",
            "name": "Electro Ramp"
        },
        {
            "tier": "Tier 3",
            "name": "Thanos Ongoing Zoo"
        },
        {
            "tier": "Tier 3",
            "name": "Thanos Death Lockjaw"
        },
        {
            "tier": "Tier 3",
            "name": "Bounce"
        },
        {
            "tier": "Tier 3",
            "name": "Cerebro 2"
        },
        {
            "tier": "Budget",
            "name": "Handsize Destroy"
        },
        {
            "tier": "Budget",
            "name": "Ongoing"
        },
        {
            "tier": "Budget",
            "name": "Sandman Kazoo"
        },
        {
            "tier": "Budget",
            "name": "Control"
        },
        {
            "tier": "Hit Monkey Nebula"
        },
        {
            "tier": "Iron Lad Patriot"
        },
        {
            "tier": "InSheNaut"
        }
    ]
}