{
    "date": "January 15, 2024",
    "Tiers": [
        {
            "tier": "Tier 1",
            "name": "Deadpool Destroy – Good in Conquest 🔼"
        },
        {
            "tier": "Tier 1",
            "name": "Good Cards Black Knight 🔼"
        },
        {
            "tier": "Tier 2",
            "name": "Lockdown – Good in Conquest 🔽"
        },
        {
            "tier": "Tier 2",
            "name": "Discard Dracula – Good in Conquest 🔙"
        },
        {
            "tier": "Tier 2",
            "name": "Thanos Control 🔽"
        },
        {
            "tier": "Tier 2",
            "name": "Sera Control – Good in Conquest 🔙"
        },
        {
            "tier": "Tier 2",
            "name": "Ongoing Tribunal 🔙"
        },
        {
            "tier": "Tier 3",
            "name": "Junk 🔙"
        },
        {
            "tier": "Tier 3",
            "name": "Shuri Sauron 🔙"
        },
        {
            "tier": "Tier 3",
            "name": "Pure Evolutionary – Good in Conquest"
        },
        {
            "tier": "Tier 3",
            "name": "Hela Lockjaw – Good in Conquest 🔽"
        },
        {
            "tier": "Tier 3",
            "name": "Thanos Lockjaw 🔽🔽"
        },
        {
            "tier": "Tier 3",
            "name": "Good Cards Darkhawk"
        },
        {
            "tier": "Tier 3",
            "name": "InSheNaut"
        },
        {
            "tier": "Tier 3",
            "name": "Loki"
        }
    ]
}